giessen_data_analysis/__init__.py
giessen_data_analysis-0.1.0.dist-info/licenses/LICENSE
giessen_data_analysis-0.1.0.dist-info/METADATA
giessen_data_analysis-0.1.0.dist-info/WHEEL
giessen_data_analysis-0.1.0.dist-info/top_level.txt
giessen_data_analysis-0.1.0.dist-info/RECORD
