Metadata-Version: 2.4
Name: giessen-data-analysis
Version: 0.1.0
Summary: Code for basic analysis of the Giessen RV pulmonary pressure trace data
Author-email: Maximilian Balmus <mbalmus@turing.ac.uk>
License: Apache-2.0
Project-URL: Homepage, https://github.com/MaxBalmus/GiessenDataAnalysis
Project-URL: Bug Reports, https://github.com/MaxBalmus/GiessenDataAnalysis/issues
Project-URL: Source, https://github.com/MaxBalmus/GiessenDataAnalysis
Classifier: Development Status :: 3 - Alpha
Classifier: Intended Audience :: Science/Research
Classifier: License :: OSI Approved :: Apache Software License
Classifier: Operating System :: OS Independent
Classifier: Programming Language :: Python :: 3
Classifier: Programming Language :: Python :: 3.8
Classifier: Programming Language :: Python :: 3.9
Classifier: Programming Language :: Python :: 3.10
Classifier: Programming Language :: Python :: 3.11
Classifier: Programming Language :: Python :: 3.12
Requires-Python: >=3.8
License-File: LICENSE
Requires-Dist: numpy
Requires-Dist: scipy
Requires-Dist: pandas
Requires-Dist: matplotlib
Requires-Dist: ipykernel
Requires-Dist: scikit-learn
Dynamic: license-file
